dicehub/__init__.py
dicehub-0.0.1.dist-info/METADATA
dicehub-0.0.1.dist-info/WHEEL
dicehub-0.0.1.dist-info/licenses/LICENSE
dicehub-0.0.1.dist-info/RECORD
