Metadata-Version: 2.1
Name: dicehub
Version: 0.0.1
Summary: dicehub-cli for deployment
Project-URL: Homepage, https://github.com/pypa/dicehub
Project-URL: Bug Tracker, https://github.com/pypa/dicehub/issues
Author-email: dicehub <info@dicehub.com>
License-File: LICENSE
Classifier: License :: OSI Approved :: MIT License
Classifier: Operating System :: OS Independent
Classifier: Programming Language :: Python :: 3
Requires-Python: >=3.7
